aclimatise/__init__.py
aclimatise/cli.py
aclimatise/cli_types.py
aclimatise/integration.py
aclimatise/model.py
aclimatise/name_generation.py
aclimatise/nlp.py
aclimatise/parser.py
aclimatise/yaml.py
aclimatise/converter/__init__.py
aclimatise/converter/cwl.py
aclimatise/converter/janis.py
aclimatise/converter/wdl.py
aclimatise/converter/yml.py
aclimatise/execution/__init__.py
aclimatise/execution/docker.py
aclimatise/execution/help.py
aclimatise/execution/local.py
aclimatise/execution/man.py
aclimatise/flag_parser/__init__.py
aclimatise/flag_parser/elements.py
aclimatise/flag_parser/parser.py
aclimatise/usage_parser/__init__.py
aclimatise/usage_parser/elements.py
aclimatise/usage_parser/model.py
aclimatise/usage_parser/parser.py
test/__init__.py
test/conftest.py
test/test_cli.py
test/test_convert.py
test/test_explore_e2e.py
test/test_model.py
test/test_parse_e2e.py
test/test_type_inference.py
test/test_yaml_dump.py
test/util.py
test/executors/__init__.py
test/executors/test_docker.py
test/executors/test_local.py
test/executors/test_man.py
test/name_generation/__init__.py
test/name_generation/conftest.py
test/name_generation/test_batch.py
test/name_generation/test_case.py
test/name_generation/test_description.py
test/name_generation/test_group.py
test/name_generation/test_single_flag.py
aclimatise-3.0.1.dist-info/LICENSE
aclimatise-3.0.1.dist-info/METADATA
aclimatise-3.0.1.dist-info/WHEEL
aclimatise-3.0.1.dist-info/entry_points.txt
aclimatise-3.0.1.dist-info/top_level.txt
aclimatise-3.0.1.dist-info/RECORD
